doppkit_toolbox/__init__.py
doppkit_toolbox/esri/arcpy/doppkit_wrapper_toolbox.py
doppkit_toolbox/esri/help/gp/Fetch_Export_grid access.xml
doppkit_toolbox/esri/toolboxes/doppkit_wrapper_toolbox.Fetch_Export.pyt.xml
doppkit_toolbox/esri/toolboxes/doppkit_wrapper_toolbox.pyt
doppkit_toolbox/esri/toolboxes/doppkit_wrapper_toolbox.pyt.xml
doppkit_esri_toolbox-0.1.7.dist-info/LICENSE
doppkit_esri_toolbox-0.1.7.dist-info/METADATA
doppkit_esri_toolbox-0.1.7.dist-info/WHEEL
doppkit_esri_toolbox-0.1.7.dist-info/top_level.txt
doppkit_esri_toolbox-0.1.7.dist-info/RECORD
