Metadata-Version: 2.1
Name: doppkit-esri-toolbox
Version: 0.1.7
Summary: Tool to allow retrival of USACE GRiD data
Maintainer-email: Ognyan Moore <ogi@hobu.co>
License: Apache License
Project-URL: homepage, https://github.com/hobuinc/doppkit-esri-toolbox
Project-URL: repository, https://github.com/hobuinc/doppkit-esri-toolbox
Classifier: Development Status :: 4 - Beta
Classifier: Intended Audience :: Information Technology
Classifier: Intended Audience :: Science/Research
Classifier: License :: OSI Approved :: Apache Software License
Classifier: Topic :: Scientific/Engineering :: GIS
Requires-Python: >=3.9
License-File: LICENSE
Requires-Dist: doppkit ==0.3.4
